pandas_airtable/__init__.py
pandas_airtable/accessor.py
pandas_airtable/batch.py
pandas_airtable/exceptions.py
pandas_airtable/py.typed
pandas_airtable/reader.py
pandas_airtable/retry.py
pandas_airtable/schema.py
pandas_airtable/types.py
pandas_airtable/utils.py
pandas_airtable-1.3.3.dist-info/METADATA
pandas_airtable-1.3.3.dist-info/WHEEL
pandas_airtable-1.3.3.dist-info/licenses/LICENSE
pandas_airtable-1.3.3.dist-info/RECORD
