Metadata-Version: 2.4
Name: pandas-airtable
Version: 1.3.3
Summary: A pandas wrapper for Airtable that provides seamless integration between pandas DataFrames and Airtable tables.
Project-URL: Homepage, https://github.com/sujal/pandas-airtable
Project-URL: Documentation, https://github.com/sujal/pandas-airtable#readme
Project-URL: Repository, https://github.com/sujal/pandas-airtable.git
Project-URL: Issues, https://github.com/sujal/pandas-airtable/issues
Project-URL: Changelog, https://github.com/sujal/pandas-airtable/blob/main/CHANGELOG.md
Author-email: Sujal Dhungana <dhunganasujal9@gmail.com>
Maintainer-email: Sujal Dhungana <dhunganasujal9@gmail.com>
License: MIT
License-File: LICENSE
Keywords: airtable,api,data,database,dataframe,etl,pandas,sync
Classifier: Development Status :: 4 - Beta
Classifier: Intended Audience :: Developers
Classifier: Intended Audience :: Science/Research
Classifier: License :: OSI Approved :: MIT License
Classifier: Operating System :: OS Independent
Classifier: Programming Language :: Python :: 3
Classifier: Programming Language :: Python :: 3 :: Only
Classifier: Programming Language :: Python :: 3.12
Classifier: Programming Language :: Python :: 3.13
Classifier: Programming Language :: Python :: 3.14
Classifier: Topic :: Database
Classifier: Topic :: Scientific/Engineering
Classifier: Topic :: Software Development :: Libraries :: Python Modules
Classifier: Typing :: Typed
Requires-Python: >=3.12
Requires-Dist: pyairtable>=3.0.0
Provides-Extra: dev
Requires-Dist: pytest-cov>=7.0.0; extra == 'dev'
Requires-Dist: pytest>=9.0.2; extra == 'dev'
Requires-Dist: python-dotenv>=1.2.1; extra == 'dev'
Requires-Dist: ruff>=0.14.10; extra == 'dev'
Provides-Extra: pandas
Requires-Dist: pandas>=2.1.3; extra == 'pandas'
